minecraft/__init__.py
txmc/__init__.py
txmc-1.2.0.dist-info/LICENSE
txmc-1.2.0.dist-info/METADATA
txmc-1.2.0.dist-info/WHEEL
txmc-1.2.0.dist-info/top_level.txt
txmc-1.2.0.dist-info/RECORD
