Metadata-Version: 2.1
Name: txmc
Version: 1.2.0
Summary: 我的编程世界Python组件
Home-page: https://gitee.com/tongxinblock/txmc
Author: 童心少年
Author-email: 363488350@qq.com
Classifier: Programming Language :: Python :: 3
Classifier: License :: OSI Approved :: MIT License
Classifier: Operating System :: OS Independent
Requires-Python: >=3.5
License-File: LICENSE
